convert_codemeta/__init__.py
convert_codemeta/codemeta_schema.jsonld
convert_codemeta/convert.py
convert_codemeta/crosswalk.csv
convert_codemeta/validate.py
convert_codemeta-0.4.0.dist-info/LICENSE
convert_codemeta-0.4.0.dist-info/LICENSE.html
convert_codemeta-0.4.0.dist-info/METADATA
convert_codemeta-0.4.0.dist-info/WHEEL
convert_codemeta-0.4.0.dist-info/top_level.txt
convert_codemeta-0.4.0.dist-info/RECORD
