Metadata-Version: 2.1
Name: convert-codemeta
Version: 0.4.0
Summary: Convert and validate codemeta.
Home-page: https://github.com/caltechlibrary/convert_codemeta
Author: Thomas E Morrell
Author-email: tmorrell@caltech.edu
License: https://data.caltech.edu/license
Download-URL: https://github.com/caltechlibrary/convert_codemeta/archive/v0.2.0.zip
Platform: UNKNOWN
Classifier: Programming Language :: Python
Classifier: Programming Language :: Python :: 3
Classifier: License :: OSI Approved :: BSD License
Requires-Dist: pandas (>=1.0.0)
Requires-Dist: pyld[requests] (==1.0.5)
Provides-Extra: all
Requires-Dist: pytest (>=6.1.1) ; extra == 'all'
Provides-Extra: tests
Requires-Dist: pytest (>=6.1.1) ; extra == 'tests'
